python_shell/__init__.py
python_shell/command.py
python_shell/exceptions.py
python_shell/interfaces.py
python_shell/command/__init__.py
python_shell/command/command.py
python_shell/command/interfaces.py
python_shell/shell/__init__.py
python_shell/shell/core.py
python_shell/shell/processing/__init__.py
python_shell/shell/processing/interfaces.py
python_shell/shell/processing/process.py
python_shell/shell/terminal/__init__.py
python_shell/shell/terminal/base.py
python_shell/shell/terminal/bash.py
python_shell/shell/terminal/interfaces.py
python_shell/util/__init__.py
python_shell/util/process.py
python_shell/util/streaming.py
python_shell/util/terminal.py
python_shell/util/version.py
tests/fixtures/__init__.py
tests/fixtures/interfaces.py
python_shell-1.0.3.dist-info/LICENSE
python_shell-1.0.3.dist-info/METADATA
python_shell-1.0.3.dist-info/WHEEL
python_shell-1.0.3.dist-info/top_level.txt
python_shell-1.0.3.dist-info/RECORD
