Metadata-Version: 2.1
Name: python-shell
Version: 1.0.3
Summary: Python Shell Wrapper library
Home-page: https://github.com/bart-tools/python-shell
Author: Alex Sokolov
Author-email: volokos.alex@gmail.com
License: UNKNOWN
Project-URL: Source, https://github.com/bart-tools/python-shell
Keywords: python shell bash
Platform: UNKNOWN
Classifier: Development Status :: 5 - Production/Stable
Classifier: Intended Audience :: Developers
Classifier: Topic :: Software Development :: Libraries :: Python Modules
Classifier: License :: OSI Approved :: MIT License
Classifier: Programming Language :: Python :: 2.7
Classifier: Programming Language :: Python :: 3.5
Classifier: Programming Language :: Python :: 3.6
Classifier: Programming Language :: Python :: 3.7
Classifier: Programming Language :: Python :: 3.8
Requires-Python: >2.7.*, !=3.0.*, !=3.1.*, !=3.2.*, !=3.3.*, !=3.4.*, <4
Requires-Dist: six (>=1.14.0)
